local_fake_useragent/__init__.py
local_fake_useragent/all_ua.py
local_fake_useragent/errors.py
local_fake_useragent/featured_ua.py
local_fake_useragent/main.py
local_fake_useragent/normal_ua.py
local_fake_useragent-2.0.1.dist-info/LICENSE
local_fake_useragent-2.0.1.dist-info/METADATA
local_fake_useragent-2.0.1.dist-info/WHEEL
local_fake_useragent-2.0.1.dist-info/top_level.txt
local_fake_useragent-2.0.1.dist-info/RECORD
